health_server/__init__.py
health_server-1.0.0.dist-info/METADATA
health_server-1.0.0.dist-info/WHEEL
health_server-1.0.0.dist-info/entry_points.txt
health_server-1.0.0.dist-info/RECORD
