Metadata-Version: 2.4
Name: health-server
Version: 1.0.0
Summary: A simple health check server using FastAPI
Author-email: treerootboy <treerootboy@gmail.com>
Requires-Python: >=3.12
Requires-Dist: fastapi
Requires-Dist: uvicorn[standard]
